BackToTheFeature/__init__.py
BackToTheFeature/back_to_the_feature.py
BackToTheFeature-0.1.0.dist-info/METADATA
BackToTheFeature-0.1.0.dist-info/WHEEL
BackToTheFeature-0.1.0.dist-info/top_level.txt
BackToTheFeature-0.1.0.dist-info/RECORD
